{
    "_1comment": "Minimum of 3 brands",
    "brands": [
        "Apple",
        "Samsung",
        "Google",
        "Huawei",
        "Xiaomi"
    ],

    "_2comment": "Minimum of 1 industry",
    "industries": [
        "global smartphone market",
        "premium laptop market",
        "smartwatch and wearable tech industry",
        "smart home ecosystem space",
        "consumer electronics sector"
    ],

    "_3comment": "Minimum of 0 personas",
    "personas": [
        "as a millennial consumer",
        "as a Gen-Z tech enthusiast",
        "as a business professional",
        "as a sustainability-conscious buyer",
        "as a design-focused creative",
        "as a price-sensitive shopper",
        "as a privacy-conscious user",
        "from the perspective of an industry analyst",
        "as a smartphone reviewer",
        "as a photographer who relies on mobile cameras"
    ],

    "_4comment": "Minimum of 3 factors",
    "comparison_factors": [
        "product quality and reliability",
        "performance and speed",
        "battery life",
        "camera system and image quality",
        "software integration and ecosystem connectivity",
        "innovation and R&D leadership",
        "design aesthetics and visual identity",
        "user interface and usability",
        "brand prestige and social status",
        "pricing and value for money",
        "environmental sustainability practices",
        "corporate ethics and data privacy",
        "after-sales support and service reliability"
    ],

    "_5comment": "Minimum of 0 temporal modifiers",
    "temporal_modifiers": [
        "historically speaking",
        "in recent years",
        "based on current market positioning",
        "looking toward future trends",
        "during the 2020s tech evolution"
    ],

    "_6comment": "Minimum of 3 product categories",
    "product_categories": [
        "smartphones",
        "laptops",
        "smartwatches",
        "wireless earbuds",
        "smart home devices",
        "AI assistants",
        "cloud storage platforms"
    ],

    "_7comment": "Minimum of 0 demographic targets",
    "demographic_targets": [
        " for busy parents",
        " for elderly users",
        " for digital natives",
        " for professionals in high-stress jobs"
    ],

    "_8comment": "Minimum of 0 usage contexts",
    "usage_contexts": [
        " during morning routines",
        " while traveling",
        " in social settings",
        " under time pressure"
    ],

    "_9comment": "Minimum of 0 temporal framing",
    "temporal_framing": [
        " in the first month of use",
        " after one year of ownership",
        " during seasonal changes"
    ]
}